odoo/addons/pos_ticket_extra_company_info/README.rst
odoo/addons/pos_ticket_extra_company_info/__init__.py
odoo/addons/pos_ticket_extra_company_info/__manifest__.py
odoo/addons/pos_ticket_extra_company_info/i18n/fr.po
odoo/addons/pos_ticket_extra_company_info/i18n/pos_ticket_extra_company_info.pot
odoo/addons/pos_ticket_extra_company_info/models/__init__.py
odoo/addons/pos_ticket_extra_company_info/models/pos_config.py
odoo/addons/pos_ticket_extra_company_info/readme/CONTRIBUTORS.rst
odoo/addons/pos_ticket_extra_company_info/readme/CREDITS.rst
odoo/addons/pos_ticket_extra_company_info/readme/DESCRIPTION.rst
odoo/addons/pos_ticket_extra_company_info/static/description/icon.png
odoo/addons/pos_ticket_extra_company_info/static/description/index.html
odoo/addons/pos_ticket_extra_company_info/static/description/ticket_no_proxy_after.png
odoo/addons/pos_ticket_extra_company_info/static/description/ticket_no_proxy_before.png
odoo/addons/pos_ticket_extra_company_info/static/src/xml/pos_ticket_extra_company_info.xml
odoo12_addon_pos_ticket_extra_company_info-12.0.1.0.2.dist-info/METADATA
odoo12_addon_pos_ticket_extra_company_info-12.0.1.0.2.dist-info/WHEEL
odoo12_addon_pos_ticket_extra_company_info-12.0.1.0.2.dist-info/top_level.txt
odoo12_addon_pos_ticket_extra_company_info-12.0.1.0.2.dist-info/RECORD
